libinspector/__init__.py
libinspector/arp_scanner.py
libinspector/arp_spoof.py
libinspector/common.py
libinspector/core.py
libinspector/global_state.py
libinspector/local_config.py
libinspector/mdns_discovery.py
libinspector/mdns_discovery_helper.py
libinspector/mem_db.py
libinspector/networking.py
libinspector/oui_parser.py
libinspector/packet_collector.py
libinspector/packet_processor.py
libinspector/privacy.py
libinspector/safe_loop.py
libinspector/ssdp_discovery.py
libinspector/tls_processor.py
libinspector/data/geolite/COPYRIGHT.txt
libinspector/data/geolite/GeoLite2-Country.mmdb
libinspector/data/geolite/LICENSE.txt
libinspector/data/geolite/README.md
libinspector/data/oui/mam.csv
libinspector/data/oui/oui.csv
libinspector/data/oui/oui36.csv
libinspector/data/trackers/README.md
libinspector/data/trackers/android-tds.json
libinspector/data/trackers/ios-tds.json
libinspector-1.0.12.dist-info/licenses/LICENSE
libinspector-1.0.12.dist-info/METADATA
libinspector-1.0.12.dist-info/WHEEL
libinspector-1.0.12.dist-info/top_level.txt
libinspector-1.0.12.dist-info/RECORD
