Metadata-Version: 2.4
Name: libinspector
Version: 1.0.12
Summary: Library for core functionalities of IoT Inspector. This captures packets and stores it in a database for real-time network traffic analysis.
Author-email: Danny Huang <dhuang@nyu.edu>, Andrew Quijano <andrew.quijano@nyu.edu>
License-Expression: Apache-2.0
Project-URL: Homepage, https://inspector.engineering.nyu.edu/
Project-URL: Source, https://github.com/nyu-mlab/inspector-core-library/
Project-URL: Tracker, https://github.com/nyu-mlab/inspector-core-library/issues
Classifier: Programming Language :: Python :: 3
Classifier: Operating System :: OS Independent
Requires-Python: >=3.11
License-File: LICENSE
Requires-Dist: setuptools==78.1.1
Requires-Dist: netaddr==1.3.0
Requires-Dist: psutil==7.0.0
Requires-Dist: scapy==2.6.1
Requires-Dist: requests==2.32.4
Requires-Dist: zeroconf==0.146.1
Dynamic: license-file
